csv_stringify/__init__.py
csv_stringify/core.py
tests/__init__.py
tests/test_core.py
csv_stringify-1.0.0.dist-info/METADATA
csv_stringify-1.0.0.dist-info/WHEEL
csv_stringify-1.0.0.dist-info/top_level.txt
csv_stringify-1.0.0.dist-info/RECORD
